restservice/__init__.py
restservice/config.py
restservice/exception.py
restservice/handler.py
restservice/service.py
restservice-0.1.9.data/data/README.md/README.md
restservice-0.1.9.dist-info/LICENSE
restservice-0.1.9.dist-info/METADATA
restservice-0.1.9.dist-info/WHEEL
restservice-0.1.9.dist-info/top_level.txt
restservice-0.1.9.dist-info/RECORD
